{
    "servers": {
        "stdlib": {
            "type": "stdio",
            "command": "uv",
            "args": [
                "run",
                "mcp_server_1_stdlib.py"
            ],
            "dev": {
                "watch": "*.py"
            }
        },
        // "library": {
        //     "type": "stdio",
        //     "command": "uv",
        //     "args": [
        //         "run",
        //         "mcp_server_2_library.py"
        //     ],
        //     "dev": {
        //         "watch": "*.py"
        //     }
        // }
    }
}
